fs_mcp/__init__.py
fs_mcp/__main__.py
fs_mcp/edit_tool.py
fs_mcp/http_runner.py
fs_mcp/server.py
fs_mcp/utils.py
fs_mcp/web_ui.py
fs_mcp-1.19.2.dist-info/METADATA
fs_mcp-1.19.2.dist-info/WHEEL
fs_mcp-1.19.2.dist-info/entry_points.txt
fs_mcp-1.19.2.dist-info/RECORD
