Metadata-Version: 2.4
Name: fs-mcp
Version: 1.19.2
Summary: A secure MCP filesystem server with Stdio and Web UI modes.
Author-email: luutuankiet <luutuankiet.ftu2@gmail.com>
Requires-Python: >=3.10
Requires-Dist: distro
Requires-Dist: fastapi>=0.128.0
Requires-Dist: fastmcp==2.14.3
Requires-Dist: google-genai>=1.56.0
Requires-Dist: httpx>=0.28.1
Requires-Dist: pydantic>=2.0
Requires-Dist: pyfiglet
Requires-Dist: streamlit-js-eval>=0.1.5
Requires-Dist: streamlit>=1.30.0
Requires-Dist: toml
